{"total": 136, "totalNotFiltered": 136, "rows": [{"id": "bur26a", "instanceSize": 26, "cutoffType": "2%<br>CCP", "Imove1": "0.00<br>0.00", "Imax1": "0<br>0", "localOptimum1": "100%<br>100%", "Imove5k": "0.00<br>0.00", "Imax5k": "0<br>0", "localOptimum5k": "100%<br>100%", "Imove50k": "0.00<br>0.00", "Imax50k": "0<br>0", "localOptimum50k": "100%<br>100%"}, {"id": "bur26b", "instanceSize": 26, "cutoffType": "2%<br>CCP", "Imove1": "0.00<br>0.00", "Imax1": "0<br>0", "localOptimum1": "100%<br>100%", "Imove5k": "0.00<br>0.00", "Imax5k": "0<br>0", "localOptimum5k": "100%<br>100%", "Imove50k": "0.00<br>0.00", "Imax50k": "0<br>0", "localOptimum50k": "100%<br>100%"}, {"id": "bur26c", "instanceSize": 26, "cutoffType": "2%<br>CCP", "Imove1": "0.00<br>0.00", "Imax1": "0<br>0", "localOptimum1": "100%<br>100%", "Imove5k": "0.00<br>0.00", "Imax5k": "0<br>0", "localOptimum5k": "100%<br>100%", "Imove50k": "0.00<br>0.00", "Imax50k": "0<br>0", "localOptimum50k": "100%<br>100%"}, {"id": "bur26d", "instanceSize": 26, "cutoffType": "2%<br>CCP", "Imove1": "0.00<br>0.00", "Imax1": "0<br>0", "localOptimum1": "100%<br>100%", "Imove5k": "0.00<br>0.00", "Imax5k": "0<br>0", "localOptimum5k": "100%<br>100%", "Imove50k": "0.00<br>0.00", "Imax50k": "0<br>0", "localOptimum50k": "100%<br>100%"}, {"id": "bur26e", "instanceSize": 26, "cutoffType": "2%<br>CCP", "Imove1": "0.00<br>0.00", "Imax1": "0<br>0", "localOptimum1": "100%<br>100%", "Imove5k": "0.00<br>0.00", "Imax5k": "0<br>0", "localOptimum5k": "100%<br>100%", "Imove50k": "0.00<br>0.00", "Imax50k": "0<br>0", "localOptimum50k": "100%<br>100%"}, {"id": "bur26f", "instanceSize": 26, "cutoffType": "2%<br>CCP", "Imove1": "0.00<br>0.00", "Imax1": "0<br>0", "localOptimum1": "100%<br>100%", "Imove5k": "0.00<br>0.00", "Imax5k": "0<br>0", "localOptimum5k": "100%<br>100%", "Imove50k": "0.00<br>0.00", "Imax50k": "0<br>0", "localOptimum50k": "100%<br>100%"}, {"id": "bur26g", "instanceSize": 26, "cutoffType": "2%<br>CCP", "Imove1": "0.00<br>0.00", "Imax1": "0<br>0", "localOptimum1": "100%<br>100%", "Imove5k": "0.00<br>0.00", "Imax5k": "0<br>0", "localOptimum5k": "100%<br>100%", "Imove50k": "0.00<br>0.00", "Imax50k": "0<br>0", "localOptimum50k": "100%<br>100%"}, {"id": "bur26h", "instanceSize": 26, "cutoffType": "2%<br>CCP", "Imove1": "0.00<br>0.00", "Imax1": "0<br>0", "localOptimum1": "100%<br>100%", "Imove5k": "0.00<br>0.00", "Imax5k": "0<br>0", "localOptimum5k": "100%<br>100%", "Imove50k": "0.00<br>0.00", "Imax50k": "0<br>0", "localOptimum50k": "100%<br>100%"}, {"id": "chr12a", "instanceSize": 12, "cutoffType": "2%<br>CCP", "Imove1": "0.00<br>0.00", "Imax1": "0<br>0", "localOptimum1": "100%<br>100%", "Imove5k": "0.00<br>0.00", "Imax5k": "0<br>0", "localOptimum5k": "100%<br>100%", "Imove50k": "0.00<br>0.00", "Imax50k": "0<br>0", "localOptimum50k": "100%<br>100%"}, {"id": "chr12b", "instanceSize": 12, "cutoffType": "2%<br>CCP", "Imove1": "0.00<br>0.01", "Imax1": "0<br>1", "localOptimum1": "100%<br>99%", "Imove5k": "0.00<br>0.00", "Imax5k": "0<br>0", "localOptimum5k": "100%<br>100%", "Imove50k": "0.00<br>0.00", "Imax50k": "0<br>0", "localOptimum50k": "100%<br>100%"}, {"id": "chr12c", "instanceSize": 12, "cutoffType": "2%<br>CCP", "Imove1": "0.00<br>0.00", "Imax1": "0<br>0", "localOptimum1": "100%<br>100%", "Imove5k": "0.00<br>0.00", "Imax5k": "0<br>0", "localOptimum5k": "100%<br>100%", "Imove50k": "0.00<br>0.00", "Imax50k": "0<br>0", "localOptimum50k": "100%<br>100%"}, {"id": "chr15a", "instanceSize": 15, "cutoffType": "2%<br>CCP", "Imove1": "0.00<br>0.00", "Imax1": "0<br>0", "localOptimum1": "100%<br>100%", "Imove5k": "0.00<br>0.00", "Imax5k": "0<br>0", "localOptimum5k": "100%<br>100%", "Imove50k": "0.00<br>0.00", "Imax50k": "0<br>0", "localOptimum50k": "100%<br>100%"}, {"id": "chr15b", "instanceSize": 15, "cutoffType": "2%<br>CCP", "Imove1": "0.00<br>0.00", "Imax1": "0<br>0", "localOptimum1": "100%<br>100%", "Imove5k": "0.00<br>0.00", "Imax5k": "0<br>0", "localOptimum5k": "100%<br>100%", "Imove50k": "0.00<br>0.00", "Imax50k": "0<br>0", "localOptimum50k": "100%<br>100%"}, {"id": "chr15c", "instanceSize": 15, "cutoffType": "2%<br>CCP", "Imove1": "0.00<br>0.00", "Imax1": "0<br>0", "localOptimum1": "100%<br>100%", "Imove5k": "0.00<br>0.00", "Imax5k": "0<br>0", "localOptimum5k": "100%<br>100%", "Imove50k": "0.00<br>0.00", "Imax50k": "0<br>0", "localOptimum50k": "100%<br>100%"}, {"id": "chr18a", "instanceSize": 18, "cutoffType": "2%<br>CCP", "Imove1": "0.00<br>0.00", "Imax1": "0<br>0", "localOptimum1": "100%<br>100%", "Imove5k": "0.00<br>0.00", "Imax5k": "0<br>0", "localOptimum5k": "100%<br>100%", "Imove50k": "0.00<br>0.00", "Imax50k": "0<br>0", "localOptimum50k": "100%<br>100%"}, {"id": "chr18b", "instanceSize": 18, "cutoffType": "2%<br>CCP", "Imove1": "0.00<br>0.01", "Imax1": "0<br>1", "localOptimum1": "100%<br>99%", "Imove5k": "0.00<br>0.00", "Imax5k": "0<br>0", "localOptimum5k": "100%<br>100%", "Imove50k": "0.00<br>0.00", "Imax50k": "0<br>0", "localOptimum50k": "100%<br>100%"}, {"id": "chr20a", "instanceSize": 20, "cutoffType": "2%<br>CCP", "Imove1": "0.00<br>0.00", "Imax1": "0<br>0", "localOptimum1": "100%<br>100%", "Imove5k": "0.00<br>0.00", "Imax5k": "0<br>0", "localOptimum5k": "100%<br>100%", "Imove50k": "0.00<br>0.00", "Imax50k": "0<br>0", "localOptimum50k": "100%<br>100%"}, {"id": "chr20b", "instanceSize": 20, "cutoffType": "2%<br>CCP", "Imove1": "0.00<br>0.00", "Imax1": "0<br>0", "localOptimum1": "100%<br>100%", "Imove5k": "0.00<br>0.00", "Imax5k": "0<br>0", "localOptimum5k": "100%<br>100%", "Imove50k": "0.00<br>0.00", "Imax50k": "0<br>0", "localOptimum50k": "100%<br>100%"}, {"id": "chr20c", "instanceSize": 20, "cutoffType": "2%<br>CCP", "Imove1": "0.00<br>0.00", "Imax1": "0<br>0", "localOptimum1": "100%<br>100%", "Imove5k": "0.00<br>0.00", "Imax5k": "0<br>0", "localOptimum5k": "100%<br>100%", "Imove50k": "0.00<br>0.00", "Imax50k": "0<br>0", "localOptimum50k": "100%<br>100%"}, {"id": "chr22a", "instanceSize": 22, "cutoffType": "2%<br>CCP", "Imove1": "0.00<br>0.00", "Imax1": "0<br>0", "localOptimum1": "100%<br>100%", "Imove5k": "0.00<br>0.00", "Imax5k": "0<br>0", "localOptimum5k": "100%<br>100%", "Imove50k": "0.00<br>0.00", "Imax50k": "0<br>0", "localOptimum50k": "100%<br>100%"}, {"id": "chr22b", "instanceSize": 22, "cutoffType": "2%<br>CCP", "Imove1": "0.00<br>0.00", "Imax1": "0<br>0", "localOptimum1": "100%<br>100%", "Imove5k": "0.00<br>0.00", "Imax5k": "0<br>0", "localOptimum5k": "100%<br>100%", "Imove50k": "0.00<br>0.00", "Imax50k": "0<br>0", "localOptimum50k": "100%<br>100%"}, {"id": "chr25a", "instanceSize": 25, "cutoffType": "2%<br>CCP", "Imove1": "0.00<br>0.00", "Imax1": "0<br>0", "localOptimum1": "100%<br>100%", "Imove5k": "0.00<br>0.00", "Imax5k": "0<br>0", "localOptimum5k": "100%<br>100%", "Imove50k": "0.00<br>0.00", "Imax50k": "0<br>0", "localOptimum50k": "100%<br>100%"}, {"id": "els19", "instanceSize": 19, "cutoffType": "2%<br>CCP", "Imove1": "0.00<br>0.00", "Imax1": "0<br>0", "localOptimum1": "100%<br>100%", "Imove5k": "0.00<br>0.00", "Imax5k": "0<br>0", "localOptimum5k": "100%<br>100%", "Imove50k": "0.00<br>0.00", "Imax50k": "0<br>0", "localOptimum50k": "100%<br>100%"}, {"id": "esc16a", "instanceSize": 16, "cutoffType": "2%<br>CCP", "Imove1": "0.00<br>0.01", "Imax1": "0<br>1", "localOptimum1": "100%<br>99%", "Imove5k": "0.00<br>0.00", "Imax5k": "0<br>0", "localOptimum5k": "100%<br>100%", "Imove50k": "0.00<br>0.00", "Imax50k": "0<br>0", "localOptimum50k": "100%<br>100%"}, {"id": "esc16b", "instanceSize": 16, "cutoffType": "2%<br>CCP", "Imove1": "0.00<br>0.00", "Imax1": "0<br>0", "localOptimum1": "100%<br>100%", "Imove5k": "0.00<br>0.00", "Imax5k": "0<br>0", "localOptimum5k": "100%<br>100%", "Imove50k": "0.00<br>0.00", "Imax50k": "0<br>0", "localOptimum50k": "100%<br>100%"}, {"id": "esc16c", "instanceSize": 16, "cutoffType": "2%<br>CCP", "Imove1": "0.00<br>0.00", "Imax1": "0<br>0", "localOptimum1": "100%<br>100%", "Imove5k": "0.00<br>0.00", "Imax5k": "0<br>0", "localOptimum5k": "100%<br>100%", "Imove50k": "0.00<br>0.00", "Imax50k": "0<br>0", "localOptimum50k": "100%<br>100%"}, {"id": "esc16d", "instanceSize": 16, "cutoffType": "2%<br>CCP", "Imove1": "0.00<br>0.03", "Imax1": "0<br>1", "localOptimum1": "100%<br>97%", "Imove5k": "0.00<br>0.00", "Imax5k": "0<br>0", "localOptimum5k": "100%<br>100%", "Imove50k": "0.00<br>0.00", "Imax50k": "0<br>0", "localOptimum50k": "100%<br>100%"}, {"id": "esc16e", "instanceSize": 16, "cutoffType": "2%<br>CCP", "Imove1": "<abbr title='p-value = 0.04550026389635839'><u>0.00</u></abbr><br>0.04", "Imax1": "0<br>1", "localOptimum1": "100%<br>96%", "Imove5k": "0.00<br>0.00", "Imax5k": "0<br>0", "localOptimum5k": "100%<br>100%", "Imove50k": "0.00<br>0.00", "Imax50k": "0<br>0", "localOptimum50k": "100%<br>100%"}, {"id": "esc16f", "instanceSize": 16, "cutoffType": "2%<br>CCP", "Imove1": "0.00<br>0.00", "Imax1": "0<br>0", "localOptimum1": "100%<br>100%", "Imove5k": "0.00<br>0.00", "Imax5k": "0<br>0", "localOptimum5k": "100%<br>100%", "Imove50k": "0.00<br>0.00", "Imax50k": "0<br>0", "localOptimum50k": "100%<br>100%"}, {"id": "esc16g", "instanceSize": 16, "cutoffType": "2%<br>CCP", "Imove1": "0.00<br>0.01", "Imax1": "0<br>1", "localOptimum1": "100%<br>99%", "Imove5k": "0.00<br>0.00", "Imax5k": "0<br>0", "localOptimum5k": "100%<br>100%", "Imove50k": "0.00<br>0.00", "Imax50k": "0<br>0", "localOptimum50k": "100%<br>100%"}, {"id": "esc16h", "instanceSize": 16, "cutoffType": "2%<br>CCP", "Imove1": "0.00<br>0.00", "Imax1": "0<br>0", "localOptimum1": "100%<br>100%", "Imove5k": "0.00<br>0.00", "Imax5k": "0<br>0", "localOptimum5k": "100%<br>100%", "Imove50k": "0.00<br>0.00", "Imax50k": "0<br>0", "localOptimum50k": "100%<br>100%"}, {"id": "esc16i", "instanceSize": 16, "cutoffType": "2%<br>CCP", "Imove1": "0.00<br>0.00", "Imax1": "0<br>0", "localOptimum1": "100%<br>100%", "Imove5k": "0.00<br>0.00", "Imax5k": "0<br>0", "localOptimum5k": "100%<br>100%", "Imove50k": "0.00<br>0.00", "Imax50k": "0<br>0", "localOptimum50k": "100%<br>100%"}, {"id": "esc16j", "instanceSize": 16, "cutoffType": "2%<br>CCP", "Imove1": "0.00<br>0.02", "Imax1": "0<br>1", "localOptimum1": "100%<br>98%", "Imove5k": "0.00<br>0.00", "Imax5k": "0<br>0", "localOptimum5k": "100%<br>100%", "Imove50k": "0.00<br>0.00", "Imax50k": "0<br>0", "localOptimum50k": "100%<br>100%"}, {"id": "esc32a", "instanceSize": 32, "cutoffType": "2%<br>CCP", "Imove1": "0.00<br>0.02", "Imax1": "0<br>2", "localOptimum1": "100%<br>99%", "Imove5k": "0.01<br>0.00", "Imax5k": "1<br>0", "localOptimum5k": "99%<br>100%", "Imove50k": "0.00<br>0.00", "Imax50k": "0<br>0", "localOptimum50k": "100%<br>100%"}, {"id": "esc32b", "instanceSize": 32, "cutoffType": "2%<br>CCP", "Imove1": "0.00<br>0.02", "Imax1": "0<br>1", "localOptimum1": "100%<br>98%", "Imove5k": "0.02<br>0.01", "Imax5k": "1<br>1", "localOptimum5k": "98%<br>99%", "Imove50k": "0.00<br>0.00", "Imax50k": "0<br>0", "localOptimum50k": "100%<br>100%"}, {"id": "esc32c", "instanceSize": 32, "cutoffType": "2%<br>CCP", "Imove1": "0.00<br>0.00", "Imax1": "0<br>0", "localOptimum1": "100%<br>100%", "Imove5k": "0.00<br>0.00", "Imax5k": "0<br>0", "localOptimum5k": "100%<br>100%", "Imove50k": "0.00<br>0.00", "Imax50k": "0<br>0", "localOptimum50k": "100%<br>100%"}, {"id": "esc32d", "instanceSize": 32, "cutoffType": "2%<br>CCP", "Imove1": "0.00<br>0.00", "Imax1": "0<br>0", "localOptimum1": "100%<br>100%", "Imove5k": "0.00<br>0.01", "Imax5k": "0<br>1", "localOptimum5k": "100%<br>99%", "Imove50k": "0.00<br>0.00", "Imax50k": "0<br>0", "localOptimum50k": "100%<br>100%"}, {"id": "esc32e", "instanceSize": 32, "cutoffType": "2%<br>CCP", "Imove1": "0.00<br>0.00", "Imax1": "0<br>0", "localOptimum1": "100%<br>100%", "Imove5k": "0.00<br>0.00", "Imax5k": "0<br>0", "localOptimum5k": "100%<br>100%", "Imove50k": "0.00<br>0.00", "Imax50k": "0<br>0", "localOptimum50k": "100%<br>100%"}, {"id": "esc32g", "instanceSize": 32, "cutoffType": "2%<br>CCP", "Imove1": "0.00<br>0.00", "Imax1": "0<br>0", "localOptimum1": "100%<br>100%", "Imove5k": "0.00<br>0.00", "Imax5k": "0<br>0", "localOptimum5k": "100%<br>100%", "Imove50k": "0.00<br>0.00", "Imax50k": "0<br>0", "localOptimum50k": "100%<br>100%"}, {"id": "esc32h", "instanceSize": 32, "cutoffType": "2%<br>CCP", "Imove1": "0.00<br>0.01", "Imax1": "0<br>1", "localOptimum1": "100%<br>99%", "Imove5k": "0.01<br>0.00", "Imax5k": "1<br>0", "localOptimum5k": "99%<br>100%", "Imove50k": "0.00<br>0.00", "Imax50k": "0<br>0", "localOptimum50k": "100%<br>100%"}, {"id": "esc64a", "instanceSize": 64, "cutoffType": "2%<br>CCP", "Imove1": "0.00<br>0.00", "Imax1": "0<br>0", "localOptimum1": "100%<br>100%", "Imove5k": "0.02<br>0.00", "Imax5k": "1<br>0", "localOptimum5k": "98%<br>100%", "Imove50k": "0.00<br>0.00", "Imax50k": "0<br>0", "localOptimum50k": "100%<br>100%"}, {"id": "esc128", "instanceSize": 128, "cutoffType": "2%<br>CCP", "Imove1": "0.01<br>0.00", "Imax1": "1<br>0", "localOptimum1": "99%<br>100%", "Imove5k": "0.39<br><abbr title='p-value = 6.808599234788902e-05'><u>0.00</u></abbr>", "Imax5k": "7<br>0", "localOptimum5k": "80%<br>100%", "Imove50k": "0.01<br>0.00", "Imax50k": "1<br>0", "localOptimum50k": "99%<br>100%"}, {"id": "had12", "instanceSize": 12, "cutoffType": "2%<br>CCP", "Imove1": "0.00<br>0.00", "Imax1": "0<br>0", "localOptimum1": "100%<br>100%", "Imove5k": "0.00<br>0.00", "Imax5k": "0<br>0", "localOptimum5k": "100%<br>100%", "Imove50k": "0.00<br>0.00", "Imax50k": "0<br>0", "localOptimum50k": "100%<br>100%"}, {"id": "had14", "instanceSize": 14, "cutoffType": "2%<br>CCP", "Imove1": "0.00<br>0.02", "Imax1": "0<br>1", "localOptimum1": "100%<br>98%", "Imove5k": "0.00<br>0.00", "Imax5k": "0<br>0", "localOptimum5k": "100%<br>100%", "Imove50k": "0.00<br>0.00", "Imax50k": "0<br>0", "localOptimum50k": "100%<br>100%"}, {"id": "had16", "instanceSize": 16, "cutoffType": "2%<br>CCP", "Imove1": "0.00<br>0.03", "Imax1": "0<br>1", "localOptimum1": "100%<br>97%", "Imove5k": "0.00<br>0.00", "Imax5k": "0<br>0", "localOptimum5k": "100%<br>100%", "Imove50k": "0.00<br>0.00", "Imax50k": "0<br>0", "localOptimum50k": "100%<br>100%"}, {"id": "had18", "instanceSize": 18, "cutoffType": "2%<br>CCP", "Imove1": "0.00<br>0.01", "Imax1": "0<br>1", "localOptimum1": "100%<br>99%", "Imove5k": "0.00<br>0.00", "Imax5k": "0<br>0", "localOptimum5k": "100%<br>100%", "Imove50k": "0.00<br>0.00", "Imax50k": "0<br>0", "localOptimum50k": "100%<br>100%"}, {"id": "had20", "instanceSize": 20, "cutoffType": "2%<br>CCP", "Imove1": "0.00<br>0.00", "Imax1": "0<br>0", "localOptimum1": "100%<br>100%", "Imove5k": "0.00<br>0.00", "Imax5k": "0<br>0", "localOptimum5k": "100%<br>100%", "Imove50k": "0.00<br>0.00", "Imax50k": "0<br>0", "localOptimum50k": "100%<br>100%"}, {"id": "kra30a", "instanceSize": 30, "cutoffType": "2%<br>CCP", "Imove1": "<abbr title='p-value = 0.04550026389635839'><u>0.00</u></abbr><br>0.04", "Imax1": "0<br>1", "localOptimum1": "100%<br>96%", "Imove5k": "0.00<br>0.00", "Imax5k": "0<br>0", "localOptimum5k": "100%<br>100%", "Imove50k": "0.00<br>0.00", "Imax50k": "0<br>0", "localOptimum50k": "100%<br>100%"}, {"id": "kra30b", "instanceSize": 30, "cutoffType": "2%<br>CCP", "Imove1": "0.00<br>0.02", "Imax1": "0<br>1", "localOptimum1": "100%<br>98%", "Imove5k": "0.00<br>0.00", "Imax5k": "0<br>0", "localOptimum5k": "100%<br>100%", "Imove50k": "0.00<br>0.00", "Imax50k": "0<br>0", "localOptimum50k": "100%<br>100%"}, {"id": "kra32", "instanceSize": 32, "cutoffType": "2%<br>CCP", "Imove1": "0.00<br>0.00", "Imax1": "0<br>0", "localOptimum1": "100%<br>100%", "Imove5k": "0.00<br>0.00", "Imax5k": "0<br>0", "localOptimum5k": "100%<br>100%", "Imove50k": "0.00<br>0.00", "Imax50k": "0<br>0", "localOptimum50k": "100%<br>100%"}, {"id": "lipa20a", "instanceSize": 20, "cutoffType": "2%<br>CCP", "Imove1": "0.00<br>0.00", "Imax1": "0<br>0", "localOptimum1": "100%<br>100%", "Imove5k": "0.00<br>0.00", "Imax5k": "0<br>0", "localOptimum5k": "100%<br>100%", "Imove50k": "0.00<br>0.00", "Imax50k": "0<br>0", "localOptimum50k": "100%<br>100%"}, {"id": "lipa20b", "instanceSize": 20, "cutoffType": "2%<br>CCP", "Imove1": "0.00<br>0.00", "Imax1": "0<br>0", "localOptimum1": "100%<br>100%", "Imove5k": "0.00<br>0.00", "Imax5k": "0<br>0", "localOptimum5k": "100%<br>100%", "Imove50k": "0.00<br>0.00", "Imax50k": "0<br>0", "localOptimum50k": "100%<br>100%"}, {"id": "lipa30a", "instanceSize": 30, "cutoffType": "2%<br>CCP", "Imove1": "0.00<br>0.00", "Imax1": "0<br>0", "localOptimum1": "100%<br>100%", "Imove5k": "0.00<br>0.00", "Imax5k": "0<br>0", "localOptimum5k": "100%<br>100%", "Imove50k": "0.00<br>0.00", "Imax50k": "0<br>0", "localOptimum50k": "100%<br>100%"}, {"id": "lipa30b", "instanceSize": 30, "cutoffType": "2%<br>CCP", "Imove1": "0.00<br>0.00", "Imax1": "0<br>0", "localOptimum1": "100%<br>100%", "Imove5k": "0.00<br>0.00", "Imax5k": "0<br>0", "localOptimum5k": "100%<br>100%", "Imove50k": "0.00<br>0.00", "Imax50k": "0<br>0", "localOptimum50k": "100%<br>100%"}, {"id": "lipa40a", "instanceSize": 40, "cutoffType": "2%<br>CCP", "Imove1": "0.00<br>0.00", "Imax1": "0<br>0", "localOptimum1": "100%<br>100%", "Imove5k": "0.00<br>0.00", "Imax5k": "0<br>0", "localOptimum5k": "100%<br>100%", "Imove50k": "0.00<br>0.00", "Imax50k": "0<br>0", "localOptimum50k": "100%<br>100%"}, {"id": "lipa40b", "instanceSize": 40, "cutoffType": "2%<br>CCP", "Imove1": "0.00<br>0.00", "Imax1": "0<br>0", "localOptimum1": "100%<br>100%", "Imove5k": "0.00<br>0.00", "Imax5k": "0<br>0", "localOptimum5k": "100%<br>100%", "Imove50k": "0.00<br>0.00", "Imax50k": "0<br>0", "localOptimum50k": "100%<br>100%"}, {"id": "lipa50a", "instanceSize": 50, "cutoffType": "2%<br>CCP", "Imove1": "0.00<br>0.00", "Imax1": "0<br>0", "localOptimum1": "100%<br>100%", "Imove5k": "0.00<br>0.00", "Imax5k": "0<br>0", "localOptimum5k": "100%<br>100%", "Imove50k": "0.00<br>0.00", "Imax50k": "0<br>0", "localOptimum50k": "100%<br>100%"}, {"id": "lipa50b", "instanceSize": 50, "cutoffType": "2%<br>CCP", "Imove1": "0.00<br>0.00", "Imax1": "0<br>0", "localOptimum1": "100%<br>100%", "Imove5k": "0.00<br>0.00", "Imax5k": "0<br>0", "localOptimum5k": "100%<br>100%", "Imove50k": "0.00<br>0.00", "Imax50k": "0<br>0", "localOptimum50k": "100%<br>100%"}, {"id": "lipa60a", "instanceSize": 60, "cutoffType": "2%<br>CCP", "Imove1": "0.00<br>0.00", "Imax1": "0<br>0", "localOptimum1": "100%<br>100%", "Imove5k": "0.00<br>0.00", "Imax5k": "0<br>0", "localOptimum5k": "100%<br>100%", "Imove50k": "0.00<br>0.00", "Imax50k": "0<br>0", "localOptimum50k": "100%<br>100%"}, {"id": "lipa60b", "instanceSize": 60, "cutoffType": "2%<br>CCP", "Imove1": "0.00<br>0.00", "Imax1": "0<br>0", "localOptimum1": "100%<br>100%", "Imove5k": "0.00<br>0.00", "Imax5k": "0<br>0", "localOptimum5k": "100%<br>100%", "Imove50k": "0.00<br>0.00", "Imax50k": "0<br>0", "localOptimum50k": "100%<br>100%"}, {"id": "lipa70a", "instanceSize": 70, "cutoffType": "2%<br>CCP", "Imove1": "0.00<br>0.00", "Imax1": "0<br>0", "localOptimum1": "100%<br>100%", "Imove5k": "0.01<br>0.00", "Imax5k": "1<br>0", "localOptimum5k": "99%<br>100%", "Imove50k": "0.00<br>0.00", "Imax50k": "0<br>0", "localOptimum50k": "100%<br>100%"}, {"id": "lipa70b", "instanceSize": 70, "cutoffType": "2%<br>CCP", "Imove1": "0.00<br>0.00", "Imax1": "0<br>0", "localOptimum1": "100%<br>100%", "Imove5k": "0.00<br>0.00", "Imax5k": "0<br>0", "localOptimum5k": "100%<br>100%", "Imove50k": "0.00<br>0.00", "Imax50k": "0<br>0", "localOptimum50k": "100%<br>100%"}, {"id": "lipa80a", "instanceSize": 80, "cutoffType": "2%<br>CCP", "Imove1": "0.00<br>0.00", "Imax1": "0<br>0", "localOptimum1": "100%<br>100%", "Imove5k": "0.01<br>0.00", "Imax5k": "1<br>0", "localOptimum5k": "99%<br>100%", "Imove50k": "0.00<br>0.00", "Imax50k": "0<br>0", "localOptimum50k": "100%<br>100%"}, {"id": "lipa80b", "instanceSize": 80, "cutoffType": "2%<br>CCP", "Imove1": "0.00<br>0.00", "Imax1": "0<br>0", "localOptimum1": "100%<br>100%", "Imove5k": "0.00<br>0.00", "Imax5k": "0<br>0", "localOptimum5k": "100%<br>100%", "Imove50k": "0.00<br>0.00", "Imax50k": "0<br>0", "localOptimum50k": "100%<br>100%"}, {"id": "lipa90a", "instanceSize": 90, "cutoffType": "2%<br>CCP", "Imove1": "0.00<br>0.00", "Imax1": "0<br>0", "localOptimum1": "100%<br>100%", "Imove5k": "0.00<br>0.00", "Imax5k": "0<br>0", "localOptimum5k": "100%<br>100%", "Imove50k": "0.00<br>0.00", "Imax50k": "0<br>0", "localOptimum50k": "100%<br>100%"}, {"id": "lipa90b", "instanceSize": 90, "cutoffType": "2%<br>CCP", "Imove1": "0.00<br>0.00", "Imax1": "0<br>0", "localOptimum1": "100%<br>100%", "Imove5k": "0.01<br>0.00", "Imax5k": "1<br>0", "localOptimum5k": "99%<br>100%", "Imove50k": "0.00<br>0.00", "Imax50k": "0<br>0", "localOptimum50k": "100%<br>100%"}, {"id": "nug12", "instanceSize": 12, "cutoffType": "2%<br>CCP", "Imove1": "0.00<br>0.01", "Imax1": "0<br>1", "localOptimum1": "100%<br>99%", "Imove5k": "0.00<br>0.00", "Imax5k": "0<br>0", "localOptimum5k": "100%<br>100%", "Imove50k": "0.00<br>0.00", "Imax50k": "0<br>0", "localOptimum50k": "100%<br>100%"}, {"id": "nug14", "instanceSize": 14, "cutoffType": "2%<br>CCP", "Imove1": "0.00<br>0.00", "Imax1": "0<br>0", "localOptimum1": "100%<br>100%", "Imove5k": "0.00<br>0.00", "Imax5k": "0<br>0", "localOptimum5k": "100%<br>100%", "Imove50k": "0.00<br>0.00", "Imax50k": "0<br>0", "localOptimum50k": "100%<br>100%"}, {"id": "nug15", "instanceSize": 15, "cutoffType": "2%<br>CCP", "Imove1": "0.00<br>0.00", "Imax1": "0<br>0", "localOptimum1": "100%<br>100%", "Imove5k": "0.00<br>0.00", "Imax5k": "0<br>0", "localOptimum5k": "100%<br>100%", "Imove50k": "0.00<br>0.00", "Imax50k": "0<br>0", "localOptimum50k": "100%<br>100%"}, {"id": "nug16a", "instanceSize": 16, "cutoffType": "2%<br>CCP", "Imove1": "0.00<br>0.00", "Imax1": "0<br>0", "localOptimum1": "100%<br>100%", "Imove5k": "0.00<br>0.00", "Imax5k": "0<br>0", "localOptimum5k": "100%<br>100%", "Imove50k": "0.00<br>0.00", "Imax50k": "0<br>0", "localOptimum50k": "100%<br>100%"}, {"id": "nug16b", "instanceSize": 16, "cutoffType": "2%<br>CCP", "Imove1": "0.00<br>0.01", "Imax1": "0<br>1", "localOptimum1": "100%<br>99%", "Imove5k": "0.00<br>0.00", "Imax5k": "0<br>0", "localOptimum5k": "100%<br>100%", "Imove50k": "0.00<br>0.00", "Imax50k": "0<br>0", "localOptimum50k": "100%<br>100%"}, {"id": "nug17", "instanceSize": 17, "cutoffType": "2%<br>CCP", "Imove1": "0.00<br>0.00", "Imax1": "0<br>0", "localOptimum1": "100%<br>100%", "Imove5k": "0.00<br>0.00", "Imax5k": "0<br>0", "localOptimum5k": "100%<br>100%", "Imove50k": "0.00<br>0.00", "Imax50k": "0<br>0", "localOptimum50k": "100%<br>100%"}, {"id": "nug18", "instanceSize": 18, "cutoffType": "2%<br>CCP", "Imove1": "0.00<br>0.00", "Imax1": "0<br>0", "localOptimum1": "100%<br>100%", "Imove5k": "0.00<br>0.00", "Imax5k": "0<br>0", "localOptimum5k": "100%<br>100%", "Imove50k": "0.00<br>0.00", "Imax50k": "0<br>0", "localOptimum50k": "100%<br>100%"}, {"id": "nug20", "instanceSize": 20, "cutoffType": "2%<br>CCP", "Imove1": "0.00<br>0.01", "Imax1": "0<br>1", "localOptimum1": "100%<br>99%", "Imove5k": "0.00<br>0.00", "Imax5k": "0<br>0", "localOptimum5k": "100%<br>100%", "Imove50k": "0.00<br>0.00", "Imax50k": "0<br>0", "localOptimum50k": "100%<br>100%"}, {"id": "nug21", "instanceSize": 21, "cutoffType": "2%<br>CCP", "Imove1": "0.00<br>0.00", "Imax1": "0<br>0", "localOptimum1": "100%<br>100%", "Imove5k": "0.00<br>0.00", "Imax5k": "0<br>0", "localOptimum5k": "100%<br>100%", "Imove50k": "0.00<br>0.00", "Imax50k": "0<br>0", "localOptimum50k": "100%<br>100%"}, {"id": "nug22", "instanceSize": 22, "cutoffType": "2%<br>CCP", "Imove1": "0.00<br>0.01", "Imax1": "0<br>1", "localOptimum1": "100%<br>99%", "Imove5k": "0.00<br>0.00", "Imax5k": "0<br>0", "localOptimum5k": "100%<br>100%", "Imove50k": "0.00<br>0.00", "Imax50k": "0<br>0", "localOptimum50k": "100%<br>100%"}, {"id": "nug24", "instanceSize": 24, "cutoffType": "2%<br>CCP", "Imove1": "0.00<br>0.03", "Imax1": "0<br>2", "localOptimum1": "100%<br>98%", "Imove5k": "0.00<br>0.00", "Imax5k": "0<br>0", "localOptimum5k": "100%<br>100%", "Imove50k": "0.00<br>0.00", "Imax50k": "0<br>0", "localOptimum50k": "100%<br>100%"}, {"id": "nug25", "instanceSize": 25, "cutoffType": "2%<br>CCP", "Imove1": "0.00<br>0.00", "Imax1": "0<br>0", "localOptimum1": "100%<br>100%", "Imove5k": "0.00<br>0.00", "Imax5k": "0<br>0", "localOptimum5k": "100%<br>100%", "Imove50k": "0.00<br>0.00", "Imax50k": "0<br>0", "localOptimum50k": "100%<br>100%"}, {"id": "nug27", "instanceSize": 27, "cutoffType": "2%<br>CCP", "Imove1": "0.00<br>0.02", "Imax1": "0<br>1", "localOptimum1": "100%<br>98%", "Imove5k": "0.00<br>0.00", "Imax5k": "0<br>0", "localOptimum5k": "100%<br>100%", "Imove50k": "0.00<br>0.00", "Imax50k": "0<br>0", "localOptimum50k": "100%<br>100%"}, {"id": "nug28", "instanceSize": 28, "cutoffType": "2%<br>CCP", "Imove1": "0.00<br>0.00", "Imax1": "0<br>0", "localOptimum1": "100%<br>100%", "Imove5k": "0.00<br>0.00", "Imax5k": "0<br>0", "localOptimum5k": "100%<br>100%", "Imove50k": "0.00<br>0.00", "Imax50k": "0<br>0", "localOptimum50k": "100%<br>100%"}, {"id": "nug30", "instanceSize": 30, "cutoffType": "2%<br>CCP", "Imove1": "0.00<br>0.00", "Imax1": "0<br>0", "localOptimum1": "100%<br>100%", "Imove5k": "0.00<br>0.00", "Imax5k": "0<br>0", "localOptimum5k": "100%<br>100%", "Imove50k": "0.00<br>0.00", "Imax50k": "0<br>0", "localOptimum50k": "100%<br>100%"}, {"id": "rou12", "instanceSize": 12, "cutoffType": "2%<br>CCP", "Imove1": "0.00<br>0.00", "Imax1": "0<br>0", "localOptimum1": "100%<br>100%", "Imove5k": "0.00<br>0.00", "Imax5k": "0<br>0", "localOptimum5k": "100%<br>100%", "Imove50k": "0.00<br>0.00", "Imax50k": "0<br>0", "localOptimum50k": "100%<br>100%"}, {"id": "rou15", "instanceSize": 15, "cutoffType": "2%<br>CCP", "Imove1": "0.00<br>0.00", "Imax1": "0<br>0", "localOptimum1": "100%<br>100%", "Imove5k": "0.00<br>0.00", "Imax5k": "0<br>0", "localOptimum5k": "100%<br>100%", "Imove50k": "0.00<br>0.00", "Imax50k": "0<br>0", "localOptimum50k": "100%<br>100%"}, {"id": "rou20", "instanceSize": 20, "cutoffType": "2%<br>CCP", "Imove1": "0.00<br>0.00", "Imax1": "0<br>0", "localOptimum1": "100%<br>100%", "Imove5k": "0.00<br>0.00", "Imax5k": "0<br>0", "localOptimum5k": "100%<br>100%", "Imove50k": "0.00<br>0.00", "Imax50k": "0<br>0", "localOptimum50k": "100%<br>100%"}, {"id": "scr12", "instanceSize": 12, "cutoffType": "2%<br>CCP", "Imove1": "0.00<br>0.00", "Imax1": "0<br>0", "localOptimum1": "100%<br>100%", "Imove5k": "0.00<br>0.00", "Imax5k": "0<br>0", "localOptimum5k": "100%<br>100%", "Imove50k": "0.00<br>0.00", "Imax50k": "0<br>0", "localOptimum50k": "100%<br>100%"}, {"id": "scr15", "instanceSize": 15, "cutoffType": "2%<br>CCP", "Imove1": "0.00<br>0.00", "Imax1": "0<br>0", "localOptimum1": "100%<br>100%", "Imove5k": "0.00<br>0.00", "Imax5k": "0<br>0", "localOptimum5k": "100%<br>100%", "Imove50k": "0.00<br>0.00", "Imax50k": "0<br>0", "localOptimum50k": "100%<br>100%"}, {"id": "scr20", "instanceSize": 20, "cutoffType": "2%<br>CCP", "Imove1": "0.00<br>0.00", "Imax1": "0<br>0", "localOptimum1": "100%<br>100%", "Imove5k": "0.00<br>0.00", "Imax5k": "0<br>0", "localOptimum5k": "100%<br>100%", "Imove50k": "0.00<br>0.00", "Imax50k": "0<br>0", "localOptimum50k": "100%<br>100%"}, {"id": "sko42", "instanceSize": 42, "cutoffType": "2%<br>CCP", "Imove1": "0.00<br>0.00", "Imax1": "0<br>0", "localOptimum1": "100%<br>100%", "Imove5k": "0.00<br>0.00", "Imax5k": "0<br>0", "localOptimum5k": "100%<br>100%", "Imove50k": "0.00<br>0.00", "Imax50k": "0<br>0", "localOptimum50k": "100%<br>100%"}, {"id": "sko49", "instanceSize": 49, "cutoffType": "2%<br>CCP", "Imove1": "0.00<br>0.02", "Imax1": "0<br>1", "localOptimum1": "100%<br>98%", "Imove5k": "0.00<br>0.00", "Imax5k": "0<br>0", "localOptimum5k": "100%<br>100%", "Imove50k": "0.00<br>0.00", "Imax50k": "0<br>0", "localOptimum50k": "100%<br>100%"}, {"id": "sko56", "instanceSize": 56, "cutoffType": "2%<br>CCP", "Imove1": "0.00<br>0.00", "Imax1": "0<br>0", "localOptimum1": "100%<br>100%", "Imove5k": "0.00<br>0.00", "Imax5k": "0<br>0", "localOptimum5k": "100%<br>100%", "Imove50k": "0.00<br>0.00", "Imax50k": "0<br>0", "localOptimum50k": "100%<br>100%"}, {"id": "sko64", "instanceSize": 64, "cutoffType": "2%<br>CCP", "Imove1": "0.00<br>0.00", "Imax1": "0<br>0", "localOptimum1": "100%<br>100%", "Imove5k": "0.00<br>0.00", "Imax5k": "0<br>0", "localOptimum5k": "100%<br>100%", "Imove50k": "0.00<br>0.00", "Imax50k": "0<br>0", "localOptimum50k": "100%<br>100%"}, {"id": "sko72", "instanceSize": 72, "cutoffType": "2%<br>CCP", "Imove1": "0.00<br>0.00", "Imax1": "0<br>0", "localOptimum1": "100%<br>100%", "Imove5k": "0.00<br>0.00", "Imax5k": "0<br>0", "localOptimum5k": "100%<br>100%", "Imove50k": "0.00<br>0.00", "Imax50k": "0<br>0", "localOptimum50k": "100%<br>100%"}, {"id": "sko81", "instanceSize": 81, "cutoffType": "2%<br>CCP", "Imove1": "0.00<br>0.01", "Imax1": "0<br>1", "localOptimum1": "100%<br>99%", "Imove5k": "0.00<br>0.00", "Imax5k": "0<br>0", "localOptimum5k": "100%<br>100%", "Imove50k": "0.00<br>0.00", "Imax50k": "0<br>0", "localOptimum50k": "100%<br>100%"}, {"id": "sko90", "instanceSize": 90, "cutoffType": "2%<br>CCP", "Imove1": "0.02<br>0.00", "Imax1": "2<br>0", "localOptimum1": "99%<br>100%", "Imove5k": "0.00<br>0.00", "Imax5k": "0<br>0", "localOptimum5k": "100%<br>100%", "Imove50k": "0.00<br>0.00", "Imax50k": "0<br>0", "localOptimum50k": "100%<br>100%"}, {"id": "sko100a", "instanceSize": 100, "cutoffType": "2%<br>CCP", "Imove1": "0.06<br>0.00", "Imax1": "2<br>0", "localOptimum1": "97%<br>100%", "Imove5k": "0.00<br>0.00", "Imax5k": "0<br>0", "localOptimum5k": "100%<br>100%", "Imove50k": "0.00<br>0.01", "Imax50k": "0<br>1", "localOptimum50k": "100%<br>99%"}, {"id": "sko100b", "instanceSize": 100, "cutoffType": "2%<br>CCP", "Imove1": "0.08<br><abbr title='p-value = 0.039359508888249725'><u>0.00</u></abbr>", "Imax1": "3<br>0", "localOptimum1": "95%<br>100%", "Imove5k": "0.00<br>0.00", "Imax5k": "0<br>0", "localOptimum5k": "100%<br>100%", "Imove50k": "0.00<br>0.00", "Imax50k": "0<br>0", "localOptimum50k": "100%<br>100%"}, {"id": "sko100c", "instanceSize": 100, "cutoffType": "2%<br>CCP", "Imove1": "0.06<br>0.00", "Imax1": "3<br>0", "localOptimum1": "97%<br>100%", "Imove5k": "0.00<br>0.00", "Imax5k": "0<br>0", "localOptimum5k": "100%<br>100%", "Imove50k": "0.00<br>0.00", "Imax50k": "0<br>0", "localOptimum50k": "100%<br>100%"}, {"id": "sko100d", "instanceSize": 100, "cutoffType": "2%<br>CCP", "Imove1": "0.06<br><abbr title='p-value = 0.03389485352468927'><u>0.00</u></abbr>", "Imax1": "2<br>0", "localOptimum1": "95%<br>100%", "Imove5k": "0.00<br>0.00", "Imax5k": "0<br>0", "localOptimum5k": "100%<br>100%", "Imove50k": "0.00<br>0.00", "Imax50k": "0<br>0", "localOptimum50k": "100%<br>100%"}, {"id": "sko100e", "instanceSize": 100, "cutoffType": "2%<br>CCP", "Imove1": "0.20<br><abbr title='p-value = 0.004016514660032747'><u>0.00</u></abbr>", "Imax1": "4<br>0", "localOptimum1": "90%<br>100%", "Imove5k": "0.00<br>0.00", "Imax5k": "0<br>0", "localOptimum5k": "100%<br>100%", "Imove50k": "0.00<br>0.00", "Imax50k": "0<br>0", "localOptimum50k": "100%<br>100%"}, {"id": "sko100f", "instanceSize": 100, "cutoffType": "2%<br>CCP", "Imove1": "0.10<br><abbr title='p-value = 0.02092133533779403'><u>0.02</u></abbr>", "Imax1": "2<br>1", "localOptimum1": "91%<br>98%", "Imove5k": "0.00<br>0.00", "Imax5k": "0<br>0", "localOptimum5k": "100%<br>100%", "Imove50k": "0.00<br>0.00", "Imax50k": "0<br>0", "localOptimum50k": "100%<br>100%"}, {"id": "ste36a", "instanceSize": 36, "cutoffType": "2%<br>CCP", "Imove1": "0.00<br>0.00", "Imax1": "0<br>0", "localOptimum1": "100%<br>100%", "Imove5k": "0.00<br>0.00", "Imax5k": "0<br>0", "localOptimum5k": "100%<br>100%", "Imove50k": "0.00<br>0.00", "Imax50k": "0<br>0", "localOptimum50k": "100%<br>100%"}, {"id": "ste36b", "instanceSize": 36, "cutoffType": "2%<br>CCP", "Imove1": "0.00<br>0.00", "Imax1": "0<br>0", "localOptimum1": "100%<br>100%", "Imove5k": "0.00<br>0.00", "Imax5k": "0<br>0", "localOptimum5k": "100%<br>100%", "Imove50k": "0.00<br>0.00", "Imax50k": "0<br>0", "localOptimum50k": "100%<br>100%"}, {"id": "ste36c", "instanceSize": 36, "cutoffType": "2%<br>CCP", "Imove1": "0.00<br>0.00", "Imax1": "0<br>0", "localOptimum1": "100%<br>100%", "Imove5k": "0.00<br>0.00", "Imax5k": "0<br>0", "localOptimum5k": "100%<br>100%", "Imove50k": "0.00<br>0.00", "Imax50k": "0<br>0", "localOptimum50k": "100%<br>100%"}, {"id": "tai10a", "instanceSize": 10, "cutoffType": "2%<br>CCP", "Imove1": "0.00<br>0.00", "Imax1": "0<br>0", "localOptimum1": "100%<br>100%", "Imove5k": "0.00<br>0.00", "Imax5k": "0<br>0", "localOptimum5k": "100%<br>100%", "Imove50k": "0.00<br>0.00", "Imax50k": "0<br>0", "localOptimum50k": "100%<br>100%"}, {"id": "tai10b", "instanceSize": 10, "cutoffType": "2%<br>CCP", "Imove1": "0.00<br>0.00", "Imax1": "0<br>0", "localOptimum1": "100%<br>100%", "Imove5k": "0.00<br>0.00", "Imax5k": "0<br>0", "localOptimum5k": "100%<br>100%", "Imove50k": "0.00<br>0.00", "Imax50k": "0<br>0", "localOptimum50k": "100%<br>100%"}, {"id": "tai12a", "instanceSize": 12, "cutoffType": "2%<br>CCP", "Imove1": "0.00<br>0.00", "Imax1": "0<br>0", "localOptimum1": "100%<br>100%", "Imove5k": "0.00<br>0.00", "Imax5k": "0<br>0", "localOptimum5k": "100%<br>100%", "Imove50k": "0.00<br>0.00", "Imax50k": "0<br>0", "localOptimum50k": "100%<br>100%"}, {"id": "tai12b", "instanceSize": 12, "cutoffType": "2%<br>CCP", "Imove1": "0.00<br>0.00", "Imax1": "0<br>0", "localOptimum1": "100%<br>100%", "Imove5k": "0.00<br>0.00", "Imax5k": "0<br>0", "localOptimum5k": "100%<br>100%", "Imove50k": "0.00<br>0.00", "Imax50k": "0<br>0", "localOptimum50k": "100%<br>100%"}, {"id": "tai15a", "instanceSize": 15, "cutoffType": "2%<br>CCP", "Imove1": "0.00<br>0.00", "Imax1": "0<br>0", "localOptimum1": "100%<br>100%", "Imove5k": "0.00<br>0.00", "Imax5k": "0<br>0", "localOptimum5k": "100%<br>100%", "Imove50k": "0.00<br>0.00", "Imax50k": "0<br>0", "localOptimum50k": "100%<br>100%"}, {"id": "tai15b", "instanceSize": 15, "cutoffType": "2%<br>CCP", "Imove1": "0.00<br>0.00", "Imax1": "0<br>0", "localOptimum1": "100%<br>100%", "Imove5k": "0.00<br>0.00", "Imax5k": "0<br>0", "localOptimum5k": "100%<br>100%", "Imove50k": "0.00<br>0.00", "Imax50k": "0<br>0", "localOptimum50k": "100%<br>100%"}, {"id": "tai17a", "instanceSize": 17, "cutoffType": "2%<br>CCP", "Imove1": "0.00<br>0.00", "Imax1": "0<br>0", "localOptimum1": "100%<br>100%", "Imove5k": "0.00<br>0.00", "Imax5k": "0<br>0", "localOptimum5k": "100%<br>100%", "Imove50k": "0.00<br>0.00", "Imax50k": "0<br>0", "localOptimum50k": "100%<br>100%"}, {"id": "tai20a", "instanceSize": 20, "cutoffType": "2%<br>CCP", "Imove1": "0.00<br>0.00", "Imax1": "0<br>0", "localOptimum1": "100%<br>100%", "Imove5k": "0.00<br>0.00", "Imax5k": "0<br>0", "localOptimum5k": "100%<br>100%", "Imove50k": "0.00<br>0.00", "Imax50k": "0<br>0", "localOptimum50k": "100%<br>100%"}, {"id": "tai20b", "instanceSize": 20, "cutoffType": "2%<br>CCP", "Imove1": "0.00<br>0.00", "Imax1": "0<br>0", "localOptimum1": "100%<br>100%", "Imove5k": "0.00<br>0.00", "Imax5k": "0<br>0", "localOptimum5k": "100%<br>100%", "Imove50k": "0.00<br>0.00", "Imax50k": "0<br>0", "localOptimum50k": "100%<br>100%"}, {"id": "tai25a", "instanceSize": 25, "cutoffType": "2%<br>CCP", "Imove1": "0.00<br>0.00", "Imax1": "0<br>0", "localOptimum1": "100%<br>100%", "Imove5k": "0.00<br>0.00", "Imax5k": "0<br>0", "localOptimum5k": "100%<br>100%", "Imove50k": "0.00<br>0.00", "Imax50k": "0<br>0", "localOptimum50k": "100%<br>100%"}, {"id": "tai25b", "instanceSize": 25, "cutoffType": "2%<br>CCP", "Imove1": "0.00<br>0.00", "Imax1": "0<br>0", "localOptimum1": "100%<br>100%", "Imove5k": "0.00<br>0.00", "Imax5k": "0<br>0", "localOptimum5k": "100%<br>100%", "Imove50k": "0.00<br>0.00", "Imax50k": "0<br>0", "localOptimum50k": "100%<br>100%"}, {"id": "tai30a", "instanceSize": 30, "cutoffType": "2%<br>CCP", "Imove1": "0.00<br>0.00", "Imax1": "0<br>0", "localOptimum1": "100%<br>100%", "Imove5k": "0.00<br>0.00", "Imax5k": "0<br>0", "localOptimum5k": "100%<br>100%", "Imove50k": "0.00<br>0.00", "Imax50k": "0<br>0", "localOptimum50k": "100%<br>100%"}, {"id": "tai30b", "instanceSize": 30, "cutoffType": "2%<br>CCP", "Imove1": "0.00<br>0.00", "Imax1": "0<br>0", "localOptimum1": "100%<br>100%", "Imove5k": "0.00<br>0.00", "Imax5k": "0<br>0", "localOptimum5k": "100%<br>100%", "Imove50k": "0.00<br>0.00", "Imax50k": "0<br>0", "localOptimum50k": "100%<br>100%"}, {"id": "tai35a", "instanceSize": 35, "cutoffType": "2%<br>CCP", "Imove1": "0.00<br>0.00", "Imax1": "0<br>0", "localOptimum1": "100%<br>100%", "Imove5k": "0.00<br>0.00", "Imax5k": "0<br>0", "localOptimum5k": "100%<br>100%", "Imove50k": "0.00<br>0.00", "Imax50k": "0<br>0", "localOptimum50k": "100%<br>100%"}, {"id": "tai35b", "instanceSize": 35, "cutoffType": "2%<br>CCP", "Imove1": "0.00<br>0.00", "Imax1": "0<br>0", "localOptimum1": "100%<br>100%", "Imove5k": "0.00<br>0.00", "Imax5k": "0<br>0", "localOptimum5k": "100%<br>100%", "Imove50k": "0.00<br>0.00", "Imax50k": "0<br>0", "localOptimum50k": "100%<br>100%"}, {"id": "tai40a", "instanceSize": 40, "cutoffType": "2%<br>CCP", "Imove1": "0.00<br>0.00", "Imax1": "0<br>0", "localOptimum1": "100%<br>100%", "Imove5k": "0.00<br>0.00", "Imax5k": "0<br>0", "localOptimum5k": "100%<br>100%", "Imove50k": "0.00<br>0.00", "Imax50k": "0<br>0", "localOptimum50k": "100%<br>100%"}, {"id": "tai40b", "instanceSize": 40, "cutoffType": "2%<br>CCP", "Imove1": "0.00<br>0.01", "Imax1": "0<br>1", "localOptimum1": "100%<br>99%", "Imove5k": "0.00<br>0.00", "Imax5k": "0<br>0", "localOptimum5k": "100%<br>100%", "Imove50k": "0.00<br>0.00", "Imax50k": "0<br>0", "localOptimum50k": "100%<br>100%"}, {"id": "tai50a", "instanceSize": 50, "cutoffType": "2%<br>CCP", "Imove1": "0.00<br>0.00", "Imax1": "0<br>0", "localOptimum1": "100%<br>100%", "Imove5k": "0.00<br>0.00", "Imax5k": "0<br>0", "localOptimum5k": "100%<br>100%", "Imove50k": "0.00<br>0.00", "Imax50k": "0<br>0", "localOptimum50k": "100%<br>100%"}, {"id": "tai50b", "instanceSize": 50, "cutoffType": "2%<br>CCP", "Imove1": "0.00<br>0.00", "Imax1": "0<br>0", "localOptimum1": "100%<br>100%", "Imove5k": "0.00<br>0.00", "Imax5k": "0<br>0", "localOptimum5k": "100%<br>100%", "Imove50k": "0.00<br>0.00", "Imax50k": "0<br>0", "localOptimum50k": "100%<br>100%"}, {"id": "tai60a", "instanceSize": 60, "cutoffType": "2%<br>CCP", "Imove1": "0.00<br>0.00", "Imax1": "0<br>0", "localOptimum1": "100%<br>100%", "Imove5k": "0.00<br>0.00", "Imax5k": "0<br>0", "localOptimum5k": "100%<br>100%", "Imove50k": "0.00<br>0.00", "Imax50k": "0<br>0", "localOptimum50k": "100%<br>100%"}, {"id": "tai60b", "instanceSize": 60, "cutoffType": "2%<br>CCP", "Imove1": "0.00<br>0.00", "Imax1": "0<br>0", "localOptimum1": "100%<br>100%", "Imove5k": "0.00<br>0.00", "Imax5k": "0<br>0", "localOptimum5k": "100%<br>100%", "Imove50k": "0.00<br>0.00", "Imax50k": "0<br>0", "localOptimum50k": "100%<br>100%"}, {"id": "tai64c", "instanceSize": 64, "cutoffType": "2%<br>CCP", "Imove1": "0.00<br>0.00", "Imax1": "0<br>0", "localOptimum1": "100%<br>100%", "Imove5k": "0.46<br><abbr title='p-value = 1.7664716814262954e-06'><u>0.00</u></abbr>", "Imax5k": "4<br>0", "localOptimum5k": "72%<br>100%", "Imove50k": "0.00<br>0.00", "Imax50k": "0<br>0", "localOptimum50k": "100%<br>100%"}, {"id": "tai80a", "instanceSize": 80, "cutoffType": "2%<br>CCP", "Imove1": "0.00<br>0.00", "Imax1": "0<br>0", "localOptimum1": "100%<br>100%", "Imove5k": "0.01<br>0.00", "Imax5k": "1<br>0", "localOptimum5k": "99%<br>100%", "Imove50k": "0.00<br>0.00", "Imax50k": "0<br>0", "localOptimum50k": "100%<br>100%"}, {"id": "tai80b", "instanceSize": 80, "cutoffType": "2%<br>CCP", "Imove1": "0.00<br>0.00", "Imax1": "0<br>0", "localOptimum1": "100%<br>100%", "Imove5k": "0.00<br>0.00", "Imax5k": "0<br>0", "localOptimum5k": "100%<br>100%", "Imove50k": "0.00<br>0.00", "Imax50k": "0<br>0", "localOptimum50k": "100%<br>100%"}, {"id": "tai100a", "instanceSize": 100, "cutoffType": "2%<br>CCP", "Imove1": "0.04<br>0.00", "Imax1": "2<br>0", "localOptimum1": "98%<br>100%", "Imove5k": "0.01<br>0.00", "Imax5k": "1<br>0", "localOptimum5k": "99%<br>100%", "Imove50k": "0.00<br>0.00", "Imax50k": "0<br>0", "localOptimum50k": "100%<br>100%"}, {"id": "tai100b", "instanceSize": 100, "cutoffType": "2%<br>CCP", "Imove1": "0.05<br><abbr title='p-value = 0.025347318677468252'><u>0.00</u></abbr>", "Imax1": "1<br>0", "localOptimum1": "95%<br>100%", "Imove5k": "0.00<br>0.00", "Imax5k": "0<br>0", "localOptimum5k": "100%<br>100%", "Imove50k": "0.00<br>0.00", "Imax50k": "0<br>0", "localOptimum50k": "100%<br>100%"}, {"id": "tai150b", "instanceSize": 150, "cutoffType": "2%<br>CCP", "Imove1": "6.71<br><abbr title='p-value = 2.4347530628967217e-17'><u>0.00</u></abbr>", "Imax1": "21<br>0", "localOptimum1": "5%<br>100%", "Imove5k": "0.00<br>0.00", "Imax5k": "0<br>0", "localOptimum5k": "100%<br>100%", "Imove50k": "0.00<br>0.00", "Imax50k": "0<br>0", "localOptimum50k": "100%<br>100%"}, {"id": "tai256c", "instanceSize": 256, "cutoffType": "2%<br>CCP", "Imove1": "2.29<br><abbr title='p-value = 7.639702242931107e-16'><u>0.00</u></abbr>", "Imax1": "10<br>0", "localOptimum1": "15%<br>100%", "Imove5k": "2.74<br><abbr title='p-value = 3.9129377171299884e-16'><u>0.00</u></abbr>", "Imax5k": "18<br>0", "localOptimum5k": "13%<br>100%", "Imove50k": "0.02<br>0.00", "Imax50k": "1<br>0", "localOptimum50k": "98%<br>100%"}, {"id": "tho30", "instanceSize": 30, "cutoffType": "2%<br>CCP", "Imove1": "0.00<br>0.00", "Imax1": "0<br>0", "localOptimum1": "100%<br>100%", "Imove5k": "0.00<br>0.00", "Imax5k": "0<br>0", "localOptimum5k": "100%<br>100%", "Imove50k": "0.00<br>0.00", "Imax50k": "0<br>0", "localOptimum50k": "100%<br>100%"}, {"id": "tho40", "instanceSize": 40, "cutoffType": "2%<br>CCP", "Imove1": "0.00<br>0.00", "Imax1": "0<br>0", "localOptimum1": "100%<br>100%", "Imove5k": "0.00<br>0.00", "Imax5k": "0<br>0", "localOptimum5k": "100%<br>100%", "Imove50k": "0.00<br>0.00", "Imax50k": "0<br>0", "localOptimum50k": "100%<br>100%"}, {"id": "tho150", "instanceSize": 150, "cutoffType": "2%<br>CCP", "Imove1": "3.76<br><abbr title='p-value = 3.12208922941051e-16'><u>0.00</u></abbr>", "Imax1": "28<br>0", "localOptimum1": "12%<br>100%", "Imove5k": "0.00<br>0.00", "Imax5k": "0<br>0", "localOptimum5k": "100%<br>100%", "Imove50k": "0.00<br>0.00", "Imax50k": "0<br>0", "localOptimum50k": "100%<br>100%"}, {"id": "wil50", "instanceSize": 50, "cutoffType": "2%<br>CCP", "Imove1": "0.00<br>0.00", "Imax1": "0<br>0", "localOptimum1": "100%<br>100%", "Imove5k": "0.00<br>0.00", "Imax5k": "0<br>0", "localOptimum5k": "100%<br>100%", "Imove50k": "0.00<br>0.00", "Imax50k": "0<br>0", "localOptimum50k": "100%<br>100%"}, {"id": "wil100", "instanceSize": 100, "cutoffType": "2%<br>CCP", "Imove1": "0.05<br>0.00", "Imax1": "3<br>0", "localOptimum1": "97%<br>100%", "Imove5k": "0.00<br>0.00", "Imax5k": "0<br>0", "localOptimum5k": "100%<br>100%", "Imove50k": "0.00<br>0.00", "Imax50k": "0<br>0", "localOptimum50k": "100%<br>100%"}]}